ntf/__init__.py
ntf/metrics.py
ntf/dataset/__init__.py
ntf/dataset/batch_iterators.py
ntf/dataset/dataset.py
ntf/dataset/datasets.py
ntf/dataset/iterator.py
ntf/examples/__init__.py
ntf/examples/images_imagenet.py
ntf/examples/images_mnist.py
ntf/examples/mnist.py
ntf/examples/example_images/ostrich.png
ntf/examples/example_images/saxophone.png
ntf/examples/example_images/mnist/0.png
ntf/examples/example_images/mnist/1.png
ntf/examples/example_images/mnist/2.png
ntf/examples/example_images/mnist/3.png
ntf/examples/example_images/mnist/4.png
ntf/examples/example_images/mnist/5.png
ntf/examples/example_images/mnist/6.png
ntf/examples/example_images/mnist/7.png
ntf/examples/example_images/mnist/8.png
ntf/examples/example_images/mnist/9.png
ntf/model/__init__.py
ntf/model/architecture.py
ntf/model/experiment.py
ntf/model/network.py
ntf/tools/__init__.py
ntf/tools/exp/__init__.py
ntf/tools/exp/exp.py
ntf/tools/tf/__init__.py
ntf/tools/tf/graph.py
ntf/tools/tf/train.py
ntf/tools/tk/__init__.py
ntf/tools/tk/canvas.py
ntf/tools/tk/event_listener.py
ntf/tools/torch/__init__.py
ntf/tools/torch/image.py
ntf/utils/__init__.py
ntf/utils/multiprocess.py
ntf/utils/utils_dataframe.py
ntf/utils/utils_files.py
ntf/utils/utils_image.py
ntf/utils/utils_io.py
ntf/utils/utils_misc.py
ntf/utils/utils_multiprocess.py
ntf/utils/utils_numbers.py
ntf/utils/utils_profiler.py
ntf/utils/utils_show.py
ntf/utils/utils_task_context.py
ntf/utils/datastructure/__init__.py
ntf/utils/datastructure/d_of.py
ntf/utils/datastructure/dashboard.py
ntf/utils/datastructure/easy_path.py
ntf/utils/datastructure/storage.py
nucleartf/__init__.py
nucleartf/metrics.py
nucleartf/dataset/__init__.py
nucleartf/dataset/batch_iterators.py
nucleartf/dataset/dataset.py
nucleartf/dataset/datasets.py
nucleartf/dataset/iterator.py
nucleartf/examples/__init__.py
nucleartf/examples/mnist.py
nucleartf/model/__init__.py
nucleartf/model/architecture.py
nucleartf/model/experiment.py
nucleartf/model/network.py
nuclear_tf-0.3.dist-info/METADATA
nuclear_tf-0.3.dist-info/WHEEL
nuclear_tf-0.3.dist-info/top_level.txt
nuclear_tf-0.3.dist-info/RECORD
