Metadata-Version: 2.1
Name: nuclear-tf
Version: 0.3
Summary: TF helpers
Home-page: https://github.com/nuclearboy95/nucleartf
Author: Jihun Yi
Author-email: t080205@gmail.com
License: MIT
Platform: UNKNOWN
